<annotation>
	<folder>train</folder>
	<filename>125.jpg</filename>
	<path>C:\Users\User\projekTA_vscode\labeling\image2\train\125.jpg</path>
	<source>
		<database>Unknown</database>
	</source>
	<size>
		<width>683</width>
		<height>384</height>
		<depth>3</depth>
	</size>
	<segmented>0</segmented>
	<object>
		<name>5000</name>
		<pose>Unspecified</pose>
		<truncated>0</truncated>
		<difficult>0</difficult>
		<bndbox>
			<xmin>169</xmin>
			<ymin>95</ymin>
			<xmax>557</xmax>
			<ymax>270</ymax>
		</bndbox>
	</object>
</annotation>
