<annotation>
	<folder>train</folder>
	<filename>306.jpg</filename>
	<path>C:\Users\User\projekTA_vscode\labeling\image2\train\306.jpg</path>
	<source>
		<database>Unknown</database>
	</source>
	<size>
		<width>385</width>
		<height>385</height>
		<depth>3</depth>
	</size>
	<segmented>0</segmented>
	<object>
		<name>100000</name>
		<pose>Unspecified</pose>
		<truncated>0</truncated>
		<difficult>0</difficult>
		<bndbox>
			<xmin>28</xmin>
			<ymin>116</ymin>
			<xmax>354</xmax>
			<ymax>260</ymax>
		</bndbox>
	</object>
</annotation>
